syslogen/__init__.py
syslogen/__main__.py
syslogen/core.py
syslogen-1.3.1.dist-info/LICENSE
syslogen-1.3.1.dist-info/METADATA
syslogen-1.3.1.dist-info/WHEEL
syslogen-1.3.1.dist-info/entry_points.txt
syslogen-1.3.1.dist-info/top_level.txt
syslogen-1.3.1.dist-info/RECORD
