Metadata-Version: 2.1
Name: syslogen
Version: 1.3.1
Summary: Easy and simple Syslog generator
Home-page: https://github.com/zakharb/syslogen
Classifier: Programming Language :: Python :: 3
Classifier: License :: OSI Approved :: GNU General Public License v3 (GPLv3)
Classifier: Intended Audience :: Developers
Requires-Python: >=3.6
License-File: LICENSE
